geopandas_postgis/__init__.py
geopandas_postgis/geopandas_postgis.py
geopandas_postgis/tests/__init__.py
geopandas_postgis/tests/config.py
geopandas_postgis/tests/test_geopandas_postgis.py
geopandas_postgis-0.2.1.dist-info/LICENSE
geopandas_postgis-0.2.1.dist-info/METADATA
geopandas_postgis-0.2.1.dist-info/WHEEL
geopandas_postgis-0.2.1.dist-info/top_level.txt
geopandas_postgis-0.2.1.dist-info/RECORD
