Metadata-Version: 2.1
Name: geopandas-postgis
Version: 0.2.1
Summary: Adds additional postgis functionality to GeoPandas
Home-page: UNKNOWN
Author: Aaron Burgess
Author-email: geoburge@gmail.com
License: MIT License
Platform: UNKNOWN
Classifier: Programming Language :: Python :: 3
Classifier: License :: OSI Approved :: MIT License
Classifier: Operating System :: OS Independent
Requires-Dist: SQLAlchemy
Requires-Dist: GeoAlchemy2
Requires-Dist: geopandas
Requires-Dist: psycopg2
